LICENSE
MANIFEST.in
README.md
pyhide.py
requirements.txt
setup.cfg
setup.py
pyhide.egg-info/PKG-INFO
pyhide.egg-info/SOURCES.txt
pyhide.egg-info/dependency_links.txt
pyhide.egg-info/requires.txt
pyhide.egg-info/top_level.txt