Metadata-Version: 2.1
Name: pyhide
Version: 1.0.0
Summary: Use steganography to hide data in images.
Home-page: https://github.com/Peter92/pyhide
Author: Peter Hunt
Author-email: peterh@blue-zoo.co.uk
License: MIT
Download-URL: https://github.com/Peter92/pyhide/archive/1.0.0.tar.gz
Project-URL: Source, https://github.com/Peter92/pyhide
Project-URL: Issues, https://github.com/Peter92/pyhide/issues
Keywords: steganography,hide,encode,image,imaging,lsb
Platform: UNKNOWN
Classifier: Development Status :: 4 - Beta
Classifier: Intended Audience :: Developers
Classifier: License :: OSI Approved :: MIT License
Classifier: Topic :: Multimedia :: Graphics
Classifier: Topic :: Multimedia :: Graphics :: Graphics Conversion
Classifier: Programming Language :: Python
Classifier: Programming Language :: Python :: 2
Classifier: Programming Language :: Python :: 2.7
Classifier: Programming Language :: Python :: 3
Classifier: Programming Language :: Python :: 3.5
Classifier: Programming Language :: Python :: 3.6
Classifier: Programming Language :: Python :: 3.7
Classifier: Programming Language :: Python :: 3.8
Requires-Python: >=2.7, !=3.0.*, !=3.1.*, !=3.2.*, !=3.3.*, !=3.4.*
